qurix/kafka/__init__.py
qurix/kafka/__version__.py
qurix/kafka/consumer.py
qurix/kafka/entities/__init__.py
qurix/kafka/entities/base.py
qurix/kafka/entities/config.py
qurix/kafka/entities/message.py
tests/__init__.py
tests/common.py
tests/test_consumer.py
tests/entities/__init__.py
tests/entities/test_base.py
tests/entities/test_config.py
tests/entities/test_message.py
tests/scripts/__init__.py
qurix_kafka_generic_consumer-0.2.0.dist-info/METADATA
qurix_kafka_generic_consumer-0.2.0.dist-info/WHEEL
qurix_kafka_generic_consumer-0.2.0.dist-info/top_level.txt
qurix_kafka_generic_consumer-0.2.0.dist-info/RECORD
